fwl_zalmoxis-26.1.6.dist-info/licenses/LICENSE.txt
zalmoxis/__init__.py
zalmoxis/__main__.py
zalmoxis/constants.py
zalmoxis/eos_functions.py
zalmoxis/eos_properties.py
zalmoxis/structure_model.py
zalmoxis/zalmoxis.py
zalmoxis/plots/plot_MR.py
zalmoxis/plots/plot_animated_pressure_density_profiles.py
zalmoxis/plots/plot_eos.py
zalmoxis/plots/plot_melting_curves.py
zalmoxis/plots/plot_phase_vs_radius.py
zalmoxis/plots/plot_profiles.py
zalmoxis/plots/plot_profiles_all_in_one.py
zalmoxis/plots/plot_ternary.py
fwl_zalmoxis-26.1.6.dist-info/METADATA
fwl_zalmoxis-26.1.6.dist-info/WHEEL
fwl_zalmoxis-26.1.6.dist-info/entry_points.txt
fwl_zalmoxis-26.1.6.dist-info/top_level.txt
fwl_zalmoxis-26.1.6.dist-info/RECORD
