Metadata-Version: 2.4
Name: fwl-zalmoxis
Version: 26.1.6
Summary: Zalmoxis (Planetary interior structure model)
Author-email: Flavia Pascal <fpascal@astro.rug.nl>
License: Apache 2.0 License
Project-URL: homepage, https://github.com/FormingWorlds/Zalmoxis
Project-URL: issues, https://github.com/FormingWorlds/Zalmoxis/issues
Project-URL: documentation, https://zalmoxis.readthedocs.io/en/latest/
Project-URL: changelog, https://github.com/FormingWorlds/Zalmoxis/releases
Keywords: Astronomy,Exoplanets
Classifier: Development Status :: 3 - Alpha
Classifier: Intended Audience :: Science/Research
Classifier: License :: OSI Approved :: Apache Software License
Classifier: Natural Language :: English
Classifier: Operating System :: OS Independent
Classifier: Programming Language :: Python :: 3
Classifier: Programming Language :: Python :: 3.12
Classifier: Programming Language :: Python :: 3.13
Classifier: Topic :: Scientific/Engineering :: Astronomy
Requires-Python: >=3.12
License-File: LICENSE.txt
Requires-Dist: numpy
Requires-Dist: scipy
Requires-Dist: toml
Requires-Dist: matplotlib
Requires-Dist: python-ternary
Requires-Dist: tqdm
Requires-Dist: osfclient
Requires-Dist: zenodo-get
Provides-Extra: develop
Requires-Dist: bump-my-version; extra == "develop"
Requires-Dist: coverage[toml]; extra == "develop"
Requires-Dist: pip-tools; extra == "develop"
Requires-Dist: pytest>=8.1; extra == "develop"
Requires-Dist: pre-commit; extra == "develop"
Requires-Dist: ruff; extra == "develop"
Requires-Dist: pytest-rich; extra == "develop"
Requires-Dist: pytest-xdist; extra == "develop"
Provides-Extra: docs
Requires-Dist: markdown-include; extra == "docs"
Requires-Dist: mkdocs; extra == "docs"
Requires-Dist: mkdocs-material; extra == "docs"
Requires-Dist: mkdocstrings[python]; extra == "docs"
Requires-Dist: pymdown-extensions; extra == "docs"
Dynamic: license-file
